[{"name":"a.","flags":{"edit":true,"god":true,"touch":true},"pos1":[307,15,325],"pos2":[312,20,340],"level":"a","whitelist":["dophat2005"]},{"name":"b.","flags":{"edit":true,"god":true,"touch":true},"pos1":[263,41,354],"pos2":[271,46,370],"level":"a","whitelist":["dophat2005"]},{"name":"c.","flags":{"edit":true,"god":true,"touch":true},"pos1":[222,37,378],"pos2":[231,42,393],"level":"a","whitelist":["dophat2005"]},{"name":"d.","flags":{"edit":true,"god":true,"touch":true},"pos1":[180,36,418],"pos2":[188,40,433],"level":"a","whitelist":["dophat2005"]},{"name":"e.","flags":{"edit":true,"god":true,"touch":true},"pos1":[89,24,415],"pos2":[98,28,430],"level":"a","whitelist":["dophat2005"]},{"name":"nopvp","flags":{"edit":true,"god":true,"touch":true},"pos1":[-9,77,30],"pos2":[-39,84,0],"level":"Plot","whitelist":["mamchannel8112"]},{"name":"pvp","flags":{"edit":true,"god":true,"touch":true},"pos1":[353,47,339],"pos2":[345,54,333],"level":"ender","whitelist":["dophat2005"]},{"name":"i1","flags":{"edit":true,"god":true,"touch":true},"pos1":[28,4,170],"pos2":[43,17,170],"level":"a","whitelist":["dophat2005"]},{"name":"i2","flags":{"edit":true,"god":true,"touch":true},"pos1":[43,4,171],"pos2":[43,17,182],"level":"a","whitelist":["dophat2005"]},{"name":"i3","flags":{"edit":true,"god":true,"touch":true},"pos1":[42,4,182],"pos2":[27,17,182],"level":"a","whitelist":["dophat2005"]},{"name":"test","flags":{"edit":true,"god":true,"touch":true},"pos1":[80,4,201],"pos2":[81,4,203],"level":"a","whitelist":["dophat2005"]},{"name":"i4","flags":{"edit":true,"god":true,"touch":true},"pos1":[59,17,154],"pos2":[16,48,194],"level":"a","whitelist":["dophat2005"]},{"name":"j2","flags":{"edit":true,"god":true,"touch":true},"pos1":[-1,35,87],"pos2":[-17,20,109],"level":"a","whitelist":["dophat2005"]},{"name":"j3","flags":{"edit":true,"god":true,"touch":true},"pos1":[-7,7,108],"pos2":[-7,20,119],"level":"a","whitelist":["dophat2005"]},{"name":"j4","flags":{"edit":true,"god":true,"touch":true},"pos1":[-7,20,119],"pos2":[8,7,119],"level":"a","whitelist":["dophat2005"]},{"name":"j5","flags":{"edit":true,"god":true,"touch":true},"pos1":[9,7,118],"pos2":[9,20,107],"level":"a","whitelist":["dophat2005"]},{"name":"j6","flags":{"edit":true,"god":true,"touch":true},"pos1":[8,7,107],"pos2":[-7,20,107],"level":"a","whitelist":["dophat2005"]},{"name":"k1","flags":{"edit":true,"god":true,"touch":true},"pos1":[-7,10,-66],"pos2":[-7,23,-77],"level":"a","whitelist":["dophat2005"]},{"name":"k2","flags":{"edit":true,"god":true,"touch":true},"pos1":[-8,10,-77],"pos2":[-23,23,-77],"level":"a","whitelist":["dophat2005"]},{"name":"k3","flags":{"edit":true,"god":true,"touch":true},"pos1":[-23,10,-76],"pos2":[-23,23,-65],"level":"a","whitelist":["dophat2005"]},{"name":"k5","flags":{"edit":true,"god":true,"touch":true},"pos1":[-40,38,-97],"pos2":[14,64,-52],"level":"a","whitelist":["dophat2005"]},{"name":"k6","flags":{"edit":true,"god":true,"touch":true},"pos1":[-40,23,-97],"pos2":[14,64,-52],"level":"a","whitelist":["dophat2005"]},{"name":"l1","flags":{"edit":true,"god":true,"touch":true},"pos1":[-203,11,101],"pos2":[-188,24,101],"level":"a","whitelist":["dophat2005"]},{"name":"l2","flags":{"edit":true,"god":true,"touch":true},"pos1":[-188,11,100],"pos2":[-188,24,89],"level":"a","whitelist":["dophat2005"]},{"name":"l3","flags":{"edit":true,"god":true,"touch":true},"pos1":[-189,11,89],"pos2":[-204,24,89],"level":"a","whitelist":["dophat2005"]},{"name":"l4","flags":{"edit":true,"god":true,"touch":true},"pos1":[-221,24,69],"pos2":[-167,65,114],"level":"a","whitelist":["dophat2005"]},{"name":"m","flags":{"edit":true,"god":true,"touch":true},"pos1":[237,24,-94],"pos2":[260,48,-27],"level":"a","whitelist":["dophat2005"]},{"name":"m1","flags":{"edit":true,"god":true,"touch":true},"pos1":[255,24,-64],"pos2":[251,7,-64],"level":"a","whitelist":["dophat2005"]},{"name":"m2","flags":{"edit":true,"god":true,"touch":true},"pos1":[266,30,-16],"pos2":[237,24,-94],"level":"a","whitelist":["dophat2005"]},{"name":"m3","flags":{"edit":true,"god":true,"touch":true},"pos1":[242,30,-19],"pos2":[237,24,-94],"level":"a","whitelist":["dophat2005"]},{"name":"n","flags":{"edit":true,"god":true,"touch":true},"pos1":[436,28,-106],"pos2":[432,11,-106],"level":"a","whitelist":["dophat2005"]},{"name":"n2","flags":{"edit":true,"god":true,"touch":true},"pos1":[418,28,-136],"pos2":[441,52,-69],"level":"a","whitelist":["dophat2005"]},{"name":"n3","flags":{"edit":true,"god":true,"touch":true},"pos1":[451,28,-137],"pos2":[423,35,-65],"level":"a","whitelist":["dophat2005"]},{"name":"0","flags":{"edit":true,"god":true,"touch":true},"pos1":[664,38,-99],"pos2":[686,62,-33],"level":"a","whitelist":["mamchannel8112"]},{"name":"o4","flags":{"edit":true,"god":true,"touch":true},"pos1":[681,37,-70],"pos2":[677,20,-70],"level":"a","whitelist":["dophat2005"]},{"name":"o","flags":{"edit":true,"god":true,"touch":true},"pos1":[664,37,-99],"pos2":[686,61,-33],"level":"a","whitelist":["dophat2005"]},{"name":"o2","flags":{"edit":true,"god":true,"touch":true},"pos1":[668,44,-29],"pos2":[694,37,-99],"level":"a","whitelist":["dophat2005"]},{"name":"p","flags":{"edit":true,"god":true,"touch":true},"pos1":[876,59,-18],"pos2":[861,33,-90],"level":"a","whitelist":["dophat2005"]},{"name":"p2","flags":{"edit":true,"god":true,"touch":true},"pos1":[891,33,-90],"pos2":[876,59,-18],"level":"a","whitelist":["dophat2005"]},{"name":"p3","flags":{"edit":true,"god":true,"touch":true},"pos1":[878,33,-61],"pos2":[874,16,-61],"level":"a","whitelist":["dophat2005"]},{"name":"o5","flags":{"edit":true,"god":true,"touch":true},"pos1":[679,65,-27],"pos2":[664,37,-99],"level":"a","whitelist":["dophat2005"]},{"name":"m4","flags":{"edit":true,"god":true,"touch":true},"pos1":[253,49,-21],"pos2":[237,24,-94],"level":"a","whitelist":["dophat2005"]},{"name":"n4","flags":{"edit":true,"god":true,"touch":true},"pos1":[434,56,-63],"pos2":[417,28,-137],"level":"a","whitelist":["dophat2005"]},{"name":"q","flags":{"edit":true,"god":true,"touch":true},"pos1":[1061,67,15],"pos2":[1046,40,-57],"level":"a","whitelist":["dophat2005"]},{"name":"q2","flags":{"edit":true,"god":true,"touch":true},"pos1":[1076,40,-57],"pos2":[1061,67,15],"level":"a","whitelist":["dophat2005"]},{"name":"q3","flags":{"edit":true,"god":true,"touch":true},"pos1":[1063,40,-28],"pos2":[1059,23,-28],"level":"a","whitelist":["dophat2005"]},{"name":"s","flags":{"edit":true,"god":true,"touch":true},"pos1":[274,3,70],"pos2":[290,18,70],"level":"a","whitelist":["dophat2005"]},{"name":"s2","flags":{"edit":true,"god":true,"touch":true},"pos1":[290,18,70],"pos2":[290,3,83],"level":"a","whitelist":["dophat2005"]},{"name":"s3","flags":{"edit":true,"god":true,"touch":true},"pos1":[289,3,84],"pos2":[273,18,84],"level":"a","whitelist":["dophat2005"]},{"name":"s4","flags":{"edit":true,"god":true,"touch":true},"pos1":[273,18,84],"pos2":[273,3,71],"level":"a","whitelist":["dophat2005"]},{"name":"s5","flags":{"edit":true,"god":true,"touch":true},"pos1":[297,17,62],"pos2":[269,45,91],"level":"a","whitelist":["dophat2005"]},{"name":"s6","flags":{"edit":true,"god":true,"touch":true},"pos1":[295,45,89],"pos2":[265,17,62],"level":"a","whitelist":["dophat2005"]},{"name":"s7","flags":{"edit":true,"god":true,"touch":true},"pos1":[297,46,91],"pos2":[265,17,62],"level":"a","whitelist":["dophat2005"]},{"name":"t","flags":{"edit":true,"god":true,"touch":true},"pos1":[149,46,106],"pos2":[149,60,93],"level":"a","whitelist":["dophat2005"]},{"name":"t2","flags":{"edit":true,"god":true,"touch":true},"pos1":[149,60,93],"pos2":[133,46,93],"level":"a","whitelist":["dophat2005"]},{"name":"t3","flags":{"edit":true,"god":true,"touch":true},"pos1":[132,46,94],"pos2":[132,60,107],"level":"a","whitelist":["dophat2005"]},{"name":"t4","flags":{"edit":true,"god":true,"touch":true},"pos1":[132,60,107],"pos2":[148,46,107],"level":"a","whitelist":["dophat2005"]},{"name":"t6","flags":{"edit":true,"god":true,"touch":true},"pos1":[124,59,85],"pos2":[161,88,114],"level":"a","whitelist":["dophat2005"]},{"name":"u","flags":{"edit":true,"god":true,"touch":true},"pos1":[390,37,133],"pos2":[374,51,133],"level":"a","whitelist":["dophat2005"]},{"name":"u2","flags":{"edit":true,"god":true,"touch":true},"pos1":[374,51,133],"pos2":[374,37,120],"level":"a","whitelist":["dophat2005"]},{"name":"u3","flags":{"edit":true,"god":true,"touch":true},"pos1":[375,37,119],"pos2":[391,51,119],"level":"a","whitelist":["dophat2005"]},{"name":"u4","flags":{"edit":true,"god":true,"touch":true},"pos1":[391,51,119],"pos2":[391,37,132],"level":"a","whitelist":["dophat2005"]},{"name":"u5","flags":{"edit":true,"god":true,"touch":true},"pos1":[366,50,111],"pos2":[398,79,140],"level":"a","whitelist":["dophat2005"]},{"name":"v","flags":{"edit":true,"god":true,"touch":true},"pos1":[519,15,113],"pos2":[535,29,113],"level":"a","whitelist":["dophat2005"]},{"name":"v2","flags":{"edit":true,"god":true,"touch":true},"pos1":[535,29,113],"pos2":[535,15,126],"level":"a","whitelist":["dophat2005"]},{"name":"v3","flags":{"edit":true,"god":true,"touch":true},"pos1":[534,15,127],"pos2":[518,29,127],"level":"a","whitelist":["dophat2005"]},{"name":"v4","flags":{"edit":true,"god":true,"touch":true},"pos1":[518,29,127],"pos2":[518,15,114],"level":"a","whitelist":["dophat2005"]},{"name":"v6","flags":{"edit":true,"god":true,"touch":true},"pos1":[510,28,105],"pos2":[542,57,134],"level":"a","whitelist":["dophat2005"]},{"name":"ww","flags":{"edit":true,"god":true,"touch":true},"pos1":[490,4,240],"pos2":[506,22,240],"level":"a","whitelist":["dophat2005"]},{"name":"w2","flags":{"edit":true,"god":true,"touch":true},"pos1":[527,22,275],"pos2":[470,50,219],"level":"a","whitelist":["dophat2005"]},{"name":"x","flags":{"edit":true,"god":true,"touch":true},"pos1":[530,13,404],"pos2":[546,31,404],"level":"a","whitelist":["dophat2005"]},{"name":"x2","flags":{"edit":true,"god":true,"touch":true},"pos1":[510,31,383],"pos2":[567,59,439],"level":"a","whitelist":["dophat2005"]},{"name":"y","flags":{"edit":true,"god":true,"touch":true},"pos1":[418,22,322],"pos2":[434,40,322],"level":"a","whitelist":["dophat2005"]},{"name":"y2","flags":{"edit":true,"god":true,"touch":true},"pos1":[398,40,301],"pos2":[455,68,357],"level":"a","whitelist":["dophat2005"]},{"name":"i6","flags":{"edit":true,"god":true,"touch":true},"pos1":[27,3,169],"pos2":[42,16,169],"level":"a","whitelist":["dophat2005"]},{"name":"i7","flags":{"edit":true,"god":true,"touch":true},"pos1":[26,3,181],"pos2":[26,16,169],"level":"a","whitelist":["dophat2005"]},{"name":"i8","flags":{"edit":true,"god":true,"touch":true},"pos1":[42,3,170],"pos2":[42,16,181],"level":"a","whitelist":["dophat2005"]},{"name":"i9","flags":{"edit":true,"god":true,"touch":true},"pos1":[41,3,169],"pos2":[26,17,169],"level":"a","whitelist":["dophat2005"]},{"name":"z","flags":{"edit":true,"god":true,"touch":true},"pos1":[10020,6,99983],"pos2":[9996,21,99983],"level":"a","whitelist":["dophat2005"]},{"name":"z2","flags":{"edit":true,"god":true,"touch":true},"pos1":[9995,21,99984],"pos2":[9995,6,100008],"level":"a","whitelist":["dophat2005"]},{"name":"z3","flags":{"edit":true,"god":true,"touch":true},"pos1":[9995,21,100009],"pos2":[10020,6,100009],"level":"a","whitelist":["dophat2005"]},{"name":"z4","flags":{"edit":true,"god":true,"touch":true},"pos1":[10021,6,100008],"pos2":[10021,21,99983],"level":"a","whitelist":["dophat2005"]},{"name":"z5","flags":{"edit":true,"god":true,"touch":true},"pos1":[10047,22,99956],"pos2":[9975,54,100029],"level":"a","whitelist":["dophat2005"]},{"name":"d7","flags":{"edit":true,"god":true,"touch":true},"pos1":[181,41,454],"pos2":[188,48,453],"level":"a","whitelist":["dophat2005"]},{"name":"c7","flags":{"edit":true,"god":true,"touch":true},"pos1":[223,42,414],"pos2":[230,49,413],"level":"a","whitelist":["dophat2005"]},{"name":"b7","flags":{"edit":true,"god":true,"touch":true},"pos1":[263,46,390],"pos2":[270,53,389],"level":"a","whitelist":["dophat2005"]},{"name":"a7","flags":{"edit":true,"god":true,"touch":true},"pos1":[307,20,361],"pos2":[314,27,360],"level":"a","whitelist":["dophat2005"]},{"name":"a6","flags":{"edit":true,"god":true,"touch":true},"pos1":[298,16,337],"pos2":[322,23,360],"level":"a","whitelist":["dophat2005"]},{"name":"a","flags":{"edit":true,"god":true,"touch":true},"pos1":[9811,29,100002],"pos2":[9772,57,100041],"level":"a","whitelist":["dophat2005"]},{"name":"a2","flags":{"edit":true,"god":true,"touch":true},"pos1":[9778,29,100023],"pos2":[9778,5,100021],"level":"a","whitelist":["dophat2005"]},{"name":"a3","flags":{"edit":true,"god":true,"touch":true},"pos1":[9792,29,100035],"pos2":[9790,5,100035],"level":"a","whitelist":["dophat2005"]},{"name":"a4","flags":{"edit":true,"god":true,"touch":true},"pos1":[9804,29,100021],"pos2":[9804,5,100023],"level":"a","whitelist":["dophat2005"]},{"name":"a5","flags":{"edit":true,"god":true,"touch":true},"pos1":[9790,29,100009],"pos2":[9792,5,100009],"level":"a","whitelist":["dophat2005"]},{"name":"b","flags":{"edit":true,"god":true,"touch":true},"pos1":[9806,28,100057],"pos2":[9761,80,100102],"level":"a","whitelist":["dophat2005"]},{"name":"c","flags":{"edit":true,"god":true,"touch":true},"pos1":[9771,29,100151],"pos2":[9816,81,100106],"level":"a","whitelist":["dophat2005"]},{"name":"d","flags":{"edit":true,"god":true,"touch":true},"pos1":[9771,29,100172],"pos2":[9816,82,100217],"level":"a","whitelist":["dophat2005"]},{"name":"e","flags":{"edit":true,"god":true,"touch":true},"pos1":[9765,58,100359],"pos2":[9816,84,100308],"level":"a","whitelist":["dophat2005"]},{"name":"e7","flags":{"edit":true,"god":true,"touch":true},"pos1":[9767,32,100309],"pos2":[9816,84,100358],"level":"a","whitelist":["dophat2005"]},{"name":"f","flags":{"edit":true,"god":true,"touch":true},"pos1":[9764,31,100374],"pos2":[9813,84,100423],"level":"a","whitelist":["dophat2005"]},{"name":"g","flags":{"edit":true,"god":true,"touch":true},"pos1":[9761,31,100439],"pos2":[9810,84,100488],"level":"a","whitelist":["dophat2005"]},{"name":"h","flags":{"edit":true,"god":true,"touch":true},"pos1":[9760,30,100498],"pos2":[9809,82,100547],"level":"a","whitelist":["dophat2005"]},{"name":"i","flags":{"edit":true,"god":true,"touch":true},"pos1":[9760,29,100550],"pos2":[9809,83,100599],"level":"a","whitelist":["dophat2005"]},{"name":"j","flags":{"edit":true,"god":true,"touch":true},"pos1":[9757,30,100632],"pos2":[9806,83,100681],"level":"a","whitelist":["dophat2005"]},{"name":"l","flags":{"edit":true,"god":true,"touch":true},"pos1":[9747,29,100810],"pos2":[9796,82,100859],"level":"a","whitelist":["dophat2005"]},{"name":"k","flags":{"edit":true,"god":true,"touch":true},"pos1":[9749,35,100920],"pos2":[9798,88,100969],"level":"a","whitelist":["dophat2005"]},{"name":"donator","flags":{"edit":true,"god":true,"touch":true},"pos1":[9845,33,100901],"pos2":[9894,86,100950],"level":"a","whitelist":["dophat2005"]},{"name":"n1","flags":{"edit":true,"god":true,"touch":true},"pos1":[9746,36,100981],"pos2":[9795,89,101030],"level":"a","whitelist":["mamchannel8112"]},{"name":"ar","flags":{"edit":true,"god":true,"touch":true},"pos1":[9828,28,99984],"pos2":[9808,97,101041],"level":"a","whitelist":["heraldicclaw597"]},{"name":"al","flags":{"edit":true,"god":true,"touch":true},"pos1":[9832,94,99979],"pos2":[9740,35,101036],"level":"a","whitelist":["heraldicclaw597"]}]